custom_error/__init__.py
custom_error/error.py
custom_error-1.0.0.dist-info/LICENSE
custom_error-1.0.0.dist-info/METADATA
custom_error-1.0.0.dist-info/WHEEL
custom_error-1.0.0.dist-info/top_level.txt
custom_error-1.0.0.dist-info/RECORD
