Metadata-Version: 2.1
Name: custom_error
Version: 1.0.0
Summary: Create your custom errors and I have control of them with Custom Error
Home-page: https://github.com/Anthonyzok521/pypi-custom-error
Author: Anthony Carrillo
Author-email: anthonyzok521@gmail.com
License: MIT License
Keywords: custom error,custom_error,python error,error,custom exception,custom,python exception,exception,custom_exception
Classifier: Programming Language :: Python :: 3
Classifier: Operating System :: OS Independent
License-File: LICENSE
Requires-Dist: colorama
